MANIFEST.in
README.txt
setup.py
docs/HISTORY.txt
docs/LICENSE.txt
src/silva/__init__.py
src/silva.app.photogallery.egg-info/PKG-INFO
src/silva.app.photogallery.egg-info/SOURCES.txt
src/silva.app.photogallery.egg-info/dependency_links.txt
src/silva.app.photogallery.egg-info/namespace_packages.txt
src/silva.app.photogallery.egg-info/requires.txt
src/silva.app.photogallery.egg-info/top_level.txt
src/silva.app.photogallery.egg-info/zip-safe
src/silva/app/__init__.py
src/silva/app/photogallery/__init__.py
src/silva/app/photogallery/configure.zcml
src/silva/app/photogallery/interfaces.py
src/silva/app/photogallery/views.py
src/silva/app/photogallery/static/gallery.css
src/silva/app/photogallery/static/gallery.js
src/silva/app/photogallery/views_templates/photogalleryview.cpt