Metadata-Version: 1.1
Name: silva.app.photogallery
Version: 1.0
Summary: Display folders as photo galleries in Silva CMS
Home-page: https://github.com/silvacms/silva.app.photogallery
Author: Sylvain Viollon
Author-email: info@infrae.com
License: BSD
Keywords: silva photo gallery
Platform: UNKNOWN
Classifier: Programming Language :: Python
